paleos/__init__.py
paleos/agemodel.py
paleos/common.py
paleos/interpolate.py
paleos-0.1.0.dist-info/LICENSE
paleos-0.1.0.dist-info/WHEEL
paleos-0.1.0.dist-info/METADATA
paleos-0.1.0.dist-info/RECORD
